{
  "number": 152,
  "date": "2026-11-29",
  "link": "WEE",
  "link_type": "category",
  "compounds": "DINKY · LITTLE · MINUTE · SLIGHT",
  "note": "DINKY, LITTLE, MINUTE and SLIGHT are all WEES",
  "clues": [
    {
      "answer": "DINKY",
      "device": "Charade",
      "parts": [
        [
          "Small",
          "def"
        ],
        [
          " dog’s head, black",
          "ind"
        ],
        [
          " (5)",
          ""
        ]
      ],
      "parse": "The definition is 'Small'; the rest of the clue builds the answer as wordplay."
    },
    {
      "answer": "LITTLE",
      "device": "Charade",
      "parts": [
        [
          "Small",
          "def"
        ],
        [
          " untruth about teetotal Liberal",
          "ind"
        ],
        [
          " (6)",
          ""
        ]
      ],
      "parse": "The definition is 'Small'; the rest of the clue builds the answer as wordplay."
    },
    {
      "answer": "MINUTE",
      "device": "Charade",
      "parts": [
        [
          "Tiny",
          "def"
        ],
        [
          " child receiving letter in Greece",
          "ind"
        ],
        [
          " (6)",
          ""
        ]
      ],
      "parse": "The definition is 'Tiny'; the rest of the clue builds the answer as wordplay."
    },
    {
      "answer": "SLIGHT",
      "device": "Double definition",
      "parts": [
        [
          "Trivial",
          "def"
        ],
        [
          " ",
          ""
        ],
        [
          "affront",
          "ind"
        ],
        [
          " (6)",
          ""
        ]
      ],
      "parse": "Double definition: trivial, and affront."
    }
  ]
}