{
  "number": 382,
  "date": "2027-07-17",
  "link": "YELLOW",
  "link_type": "category",
  "compounds": "CANARY · GOLD · LEMON · MUSTARD",
  "note": "CANARY, GOLD, LEMON and MUSTARD are all YELLOWS",
  "clues": [
    {
      "answer": "CANARY",
      "device": "Charade",
      "parts": [
        [
          "Bird",
          "def"
        ],
        [
          " call receiving an answer",
          "ind"
        ],
        [
          " (6)",
          ""
        ]
      ],
      "parse": "The definition is 'Bird'; the rest of the clue builds the answer as wordplay."
    },
    {
      "answer": "GOLD",
      "device": "Charade",
      "parts": [
        [
          "Mercury maybe has got left inside ",
          "ind"
        ],
        [
          "precious metal",
          "def"
        ],
        [
          " (4)",
          ""
        ]
      ],
      "parse": "The definition is 'precious metal'; the rest of the clue builds the answer as wordplay."
    },
    {
      "answer": "LEMON",
      "device": "Hidden word",
      "parts": [
        [
          "Fruit",
          "def"
        ],
        [
          " found in Jerusalem once",
          "ind"
        ],
        [
          " (5)",
          ""
        ]
      ],
      "parse": "Hidden word — the definition is 'Fruit'; the answer is concealed in the surrounding wordplay."
    },
    {
      "answer": "MUSTARD",
      "device": "Charade",
      "parts": [
        [
          "Relish",
          "def"
        ],
        [
          " slander involving celebrity",
          "ind"
        ],
        [
          " (7)",
          ""
        ]
      ],
      "parse": "The definition is 'Relish'; the rest of the clue builds the answer as wordplay."
    }
  ]
}