{
  "number": 583,
  "date": "2028-02-03",
  "link": "MULTITUDE",
  "link_type": "category",
  "compounds": "DROVE · HOST · MASS · PACK",
  "note": "DROVE, HOST, MASS and PACK are all MULTITUDES",
  "clues": [
    {
      "answer": "DROVE",
      "device": "Charade",
      "parts": [
        [
          "Army",
          "def"
        ],
        [
          " doctor has done with cut",
          "ind"
        ],
        [
          " (5)",
          ""
        ]
      ],
      "parse": "The definition is 'Army'; the rest of the clue builds the answer as wordplay."
    },
    {
      "answer": "HOST",
      "device": "Double definition",
      "parts": [
        [
          "Organiser of party",
          "def"
        ],
        [
          " — ",
          ""
        ],
        [
          "lots of people",
          "ind"
        ],
        [
          " (4)",
          ""
        ]
      ],
      "parse": "Double definition: organiser of party, and lots of people."
    },
    {
      "answer": "MASS",
      "device": "Charade",
      "parts": [
        [
          "Abbreviated state ",
          "ind"
        ],
        [
          "service",
          "def"
        ],
        [
          " (4)",
          ""
        ]
      ],
      "parse": "The definition is 'service'; the rest of the clue builds the answer as wordplay."
    },
    {
      "answer": "PACK",
      "device": "Charade",
      "parts": [
        [
          "Put lots of people on ",
          "ind"
        ],
        [
          "deck",
          "def"
        ],
        [
          " (4)",
          ""
        ]
      ],
      "parse": "The definition is 'deck'; the rest of the clue builds the answer as wordplay."
    }
  ]
}